anysection/__init__.py
anysection/area.py
anysection/fiber.py
anysection/gauss_tables.py
anysection/material.py
anysection/points.py
anysection/section.py
anysection/solver.py
anysection/utils/__init__.py
anysection/utils/globals.py
anysection-1.0.0.dist-info/licenses/LICENSE
anysection-1.0.0.dist-info/METADATA
anysection-1.0.0.dist-info/WHEEL
anysection-1.0.0.dist-info/top_level.txt
anysection-1.0.0.dist-info/RECORD
