Metadata-Version: 2.4
Name: AnySection
Version: 1.0.0
Summary: A Python library for section-based moment-curvature analysis
Home-page: https://github.com/iammix/anysection
Author: Konstantinos Mixios
Author-email: Konstantinos Mixios <k.mixios@gmail.com>
License: MIT
Project-URL: Homepage, https://github.com/iammix/anysection
Requires-Python: >=3.9
License-File: LICENSE
Requires-Dist: alabaster==1.0.0
Requires-Dist: babel==2.17.0
Requires-Dist: certifi==2025.1.31
Requires-Dist: charset-normalizer==3.4.1
Requires-Dist: colorama==0.4.6
Requires-Dist: contourpy==1.3.1
Requires-Dist: cycler==0.12.1
Requires-Dist: docutils==0.21.2
Requires-Dist: fonttools==4.56.0
Requires-Dist: idna==3.10
Requires-Dist: imagesize==1.4.1
Requires-Dist: Jinja2==3.1.5
Requires-Dist: kiwisolver==1.4.8
Requires-Dist: markdown-it-py==3.0.0
Requires-Dist: MarkupSafe==3.0.2
Requires-Dist: matplotlib==3.10.0
Requires-Dist: mdit-py-plugins==0.4.2
Requires-Dist: mdurl==0.1.2
Requires-Dist: myst-parser==4.0.1
Requires-Dist: numpy==2.2.3
Requires-Dist: packaging==24.2
Requires-Dist: pillow==11.1.0
Requires-Dist: Pygments==2.19.1
Requires-Dist: pyparsing==3.2.1
Requires-Dist: python-dateutil==2.9.0.post0
Requires-Dist: PyYAML==6.0.2
Requires-Dist: requests==2.32.3
Requires-Dist: roman-numerals-py==3.1.0
Requires-Dist: scipy==1.15.2
Requires-Dist: setuptools==75.8.0
Requires-Dist: six==1.17.0
Requires-Dist: snowballstemmer==2.2.0
Requires-Dist: Sphinx==8.2.1
Requires-Dist: sphinx-autodoc-typehints==3.1.0
Requires-Dist: sphinx-rtd-theme==3.0.2
Requires-Dist: sphinxcontrib-applehelp==2.0.0
Requires-Dist: sphinxcontrib-devhelp==2.0.0
Requires-Dist: sphinxcontrib-htmlhelp==2.1.0
Requires-Dist: sphinxcontrib-jquery==4.1
Requires-Dist: sphinxcontrib-jsmath==1.0.1
Requires-Dist: sphinxcontrib-qthelp==2.0.0
Requires-Dist: sphinxcontrib-serializinghtml==2.0.0
Requires-Dist: urllib3==2.3.0
Dynamic: license-file
